README.md
setup.py
keras_progbar/__init__.py
keras_progbar/keras_progbar.py
keras_progbar.egg-info/PKG-INFO
keras_progbar.egg-info/SOURCES.txt
keras_progbar.egg-info/dependency_links.txt
keras_progbar.egg-info/entry_points.txt
keras_progbar.egg-info/requires.txt
keras_progbar.egg-info/top_level.txt