Metadata-Version: 2.1
Name: keras-progbar
Version: 1.0.0
Summary: the progbar in keras, separating it to use in pytorch. I didn't write this package, the keras-team did
Home-page: https://github.com/adamleo/keras_progbar
Author: Adam Liu
Author-email: adamhleo@gmail.com
License: MIT
Platform: UNKNOWN
Classifier: License :: OSI Approved :: MIT License
Classifier: Programming Language :: Python :: 3
Classifier: Programming Language :: Python :: 3.6
